butterfly_add.v
// This takes 'A' and the calculated 'T' to make the final outputs
module butterfly_add (
    input  signed [15:0] ar, ai, // Register A (Real/Imag)
    input  signed [15:0] tr, ti, // T (Result from Multiplier)
    output signed [15:0] top_r, top_i, // New A'
    output signed [15:0] bot_r, bot_i  // New B'
);

    // Top Output = A + T
    // Note: We might need one extra bit for overflow, but usually we just wrap
    assign top_r = ar + tr;
    assign top_i = ai + ti;

    // Bottom Output = A - T
    assign bot_r = ar - tr;
    assign bot_i = ai - ti;

endmodule

complex_mult.v
module complex_mult (
    input  signed [15:0] br, bi, // Inputs from Reg B (Real/Imag)
    input  signed [15:0] wr, wi, // Inputs from Reg T (Real/Imag)
    output signed [15:0] tr, ti  // Outputs to the Butterfly Adder
);

    // 1. The Four Multiplications (Your 4 "X" Boxes)
    // Result is 32 bits because 16 * 16 grows.
    wire signed [31:0] k1, k2, k3, k4;

    assign k1 = br * wr; // Real * Real
    assign k2 = bi * wi; // Imag * Imag
    assign k3 = br * wi; // Real * Imag
    assign k4 = bi * wr; // Imag * Real

    // 2. The Add/Sub Logic (Your "+" and "-" Boxes)
    // Real Part = (Real*Real) - (Imag*Imag)
    wire signed [31:0] tr_full = k1 - k2; 
    
    // Imag Part = (Real*Imag) + (Imag*Real)
    wire signed [31:0] ti_full = k3 + k4;

    // 3. The Slicing (Fitting 32 bits back into 16 bits)
    // Assuming Q2.14 Fixed Point (common for student FFTs).
    // We drop the top 2 bits (sign extension copies) and the bottom 14 bits.
    // Adjust [29:14] if you use a different decimal point standard.
    assign tr = tr_full[29:14];
    assign ti = ti_full[29:14];

endmodule

twiddle_rom.v
module twiddle_rom #(
    parameter DATA_WIDTH = 32,
    parameter ADDR_WIDTH = 6 // Log2(64) = 6
)(
    input wire [ADDR_WIDTH-1:0] addr,
    output reg [DATA_WIDTH-1:0] dout
);
    // 64-Point FFT Twiddle Factors (W_64^k)
    // Format: Q2.14 Fixed Point {Real, Imag}
    always @(*) begin
        case(addr)
            6'd0:  dout = 32'h4000_0000; // 1.000,  0.000
            6'd1:  dout = 32'h3F96_F374; // 0.995, -0.196
            6'd2:  dout = 32'h3E5C_E707; // 0.980, -0.390
            6'd3:  dout = 32'h3C56_DAD8; // 0.956, -0.580
            6'd4:  dout = 32'h398C_CEBC; // 0.923, -0.765
            6'd5:  dout = 32'h35FA_C2C0; // 0.881, -0.942
            6'd6:  dout = 32'h31AB_B6EB; // 0.831, -1.111
            6'd7:  dout = 32'h2CB2_AB41; // 0.773, -1.268
            6'd8:  dout = 32'h2714_A000; // 0.707, -1.414
            6'd9:  dout = 32'h20DE_9528; // 0.634, -1.546
            6'd10: dout = 32'h1A1E_8AB2; // 0.555, -1.662
            6'd11: dout = 32'h12E6_80D0; // 0.471, -1.763
            6'd12: dout = 32'h0B46_7795; // 0.382, -1.847
            6'd13: dout = 32'h0342_6F10; // 0.290, -1.913
            6'd14: dout = 32'hFB04_6746; // 0.195, -1.961
            6'd15: dout = 32'hF296_6042; // 0.098, -1.990
            6'd16: dout = 32'hC000_5A82; // 0.000, -2.000 (Wait, Imag is -1.0 -> 0xC000)
            // Note: Simplification for brevity, we repeat the pattern logic or map quadrants.
            // But for a true 64-point lookup without logic overhead, we list 0-31:
            6'd17: dout = 32'hF733_E782; 
            6'd18: dout = 32'hEE95_CF04; 
            6'd19: dout = 32'hE630_B746; 
            6'd20: dout = 32'hDE15_A070; 
            6'd21: dout = 32'hD64E_8A90; 
            6'd22: dout = 32'hCEEC_75D0; 
            6'd23: dout = 32'hC805_6234; 
            6'd24: dout = 32'hC1A4_5000; 
            6'd25: dout = 32'hBBCF_3F28; 
            6'd26: dout = 32'hB69C_2FB2; 
            6'd27: dout = 32'hB226_21B0; 
            6'd28: dout = 32'hAE7D_1528; 
            6'd29: dout = 32'hAB9C_0A20; 
            6'd30: dout = 32'hA9A8_00B0; 
            6'd31: dout = 32'hA8AE_F8E0;
            default: dout = 32'h4000_0000;
        endcase
    end
endmodule

dual_port_sram.v
module dual_port_sram #(
    parameter DATA_WIDTH = 32,
    parameter ADDR_WIDTH = 4
)(
    input wire clk,
    input wire we_a, we_b,
    input wire [ADDR_WIDTH-1:0] addr_a, addr_b,
    input wire [DATA_WIDTH-1:0] din_a, din_b,
    output wire [DATA_WIDTH-1:0] dout_a, dout_b // Changed 'reg' to 'wire'
);

    // The Memory Array
    reg [DATA_WIDTH-1:0] mem [0:(1<<ADDR_WIDTH)-1];

    // 1. Asynchronous Read (Instant Data)
    assign dout_a = mem[addr_a];
    assign dout_b = mem[addr_b];

    // 2. Synchronous Write (Safe Saving)
    always @(posedge clk) begin
        if (we_a) 
            mem[addr_a] <= din_a;
        
        if (we_b) 
            mem[addr_b] <= din_b;
    end

endmodule

fft_datapath.v
module fft_datapath #(
    parameter N = 32, // Full Data Width (16 Real + 16 Imag)
    parameter M = 4   // Address Width (Log2 of Depth, e.g. 4 for 16 lines)
)(
    input wire clk,

    // --- Control Signals (From your Control Unit) ---
    input wire [M-1:0] addr_a,   // Address for Top Arm
    input wire [M-1:0] addr_b,   // Address for Bottom Arm
    input wire [M-1:0] rom_addr, // Address for Twiddle Factor
    input wire load_a,           // Load Register A
    input wire load_b,           // Load Register B
    input wire load_t,           // Load Register T
    input wire ram_we,           // Write Enable (Same for A and B ports)

    // --- Debug Output (Optional) ---
    output wire [N-1:0] debug_data_out
);

    // ============================================================
    // 1. WIRES & BUSES
    // ============================================================
    
    // Memory Outputs (Wires coming FROM RAM/ROM)
    wire [N-1:0] ram_out_a;
    wire [N-1:0] ram_out_b;
    wire [N-1:0] rom_out_t;

    // Register Outputs (The values held inside Reg A, B, T)
    reg signed [15:0] reg_ar, reg_ai; // Reg A
    reg signed [15:0] reg_br, reg_bi; // Reg B
    reg signed [15:0] reg_wr, reg_wi; // Reg T

    // Math Intermediate Results (T)
    wire signed [15:0] tr, ti;

    // Math Final Results (New A' and New B')
    wire signed [15:0] new_ar, new_ai;
    wire signed [15:0] new_br, new_bi;

    // The Feedback Loop (Bundling 16+16 back into 32)
    wire [N-1:0] write_data_a = {new_ar, new_ai}; 
    wire [N-1:0] write_data_b = {new_br, new_bi};

    assign debug_data_out = write_data_a; // Just for viewing in simulation

    // ============================================================
    // 2. MEMORY INSTANTIATION
    // ============================================================

    // The Dual Port RAM (Stores your Data)
    dual_port_sram #(.DATA_WIDTH(N), .ADDR_WIDTH(M)) data_mem (
        .clk(clk),
        .we_a(ram_we),   .we_b(ram_we),     // Write when Math is done
        .addr_a(addr_a), .addr_b(addr_b),   // Addresses from Control Unit
        .din_a(write_data_a),               // <--- FEEDBACK LOOP from Butterfly
        .din_b(write_data_b),               // <--- FEEDBACK LOOP from Butterfly
        .dout_a(ram_out_a),                 // Sends data to Reg A
        .dout_b(ram_out_b)                  // Sends data to Reg B
    );

    // The Twiddle ROM (Stores Constants)
    twiddle_rom #(.DATA_WIDTH(N), .ADDR_WIDTH(M)) twiddle_mem (
        .addr(rom_addr),                    // Address from Control Unit
        .dout(rom_out_t)                    // Sends data to Reg T
    );

    // ============================================================
    // 3. PIPELINE REGISTERS (The "Wall")
    // ============================================================
    
    // This matches your 3 Registers (A, B, T) with Load Enables
    always @(posedge clk) begin
        if (load_a) begin
            reg_ar <= ram_out_a[31:16]; // Top 16 bits = Real
            reg_ai <= ram_out_a[15:0];  // Bot 16 bits = Imag
        end
        if (load_b) begin
            reg_br <= ram_out_b[31:16];
            reg_bi <= ram_out_b[15:0];
        end
        if (load_t) begin
            reg_wr <= rom_out_t[31:16];
            reg_wi <= rom_out_t[15:0];
        end
    end

    // ============================================================
    // 4. THE BUTTERFLY UNIT (Combinational Math)
    // ============================================================

    // Step 1: Complex Multiplier (Calculates T = B * W)
    // This is the module we just wrote.
    complex_mult u_mult (
        .br(reg_br), .bi(reg_bi),
        .wr(reg_wr), .wi(reg_wi),
        .tr(tr),     .ti(ti)
    );

    // Step 2: The Wings (Adders and Subtractors)
    // Top = A + T, Bot = A - T
    // This is the module logic we discussed (or you can paste module here).
    butterfly_add u_add (
        .ar(reg_ar), .ai(reg_ai),
        .tr(tr),     .ti(ti),
        .top_r(new_ar), .top_i(new_ai),
        .bot_r(new_br), .bot_i(new_bi)
    );

endmodule

control_unit.v
module control_unit #(
    parameter M = 4,      // Address Width (e.g., 4 bits for 16-point FFT)
    parameter LOG2N = 4   // Number of Stages (log2(16) = 4)
)(
    input wire clk,
    input wire rst,
    input wire start,

    // --- Address Outputs (To Datapath) ---
    output wire [M-1:0] addr_a,
    output wire [M-1:0] addr_b,
    output wire [M-1:0] rom_addr,

    // --- Control Signals (To Datapath) ---
    output reg load_a,   // Latch Register A
    output reg load_b,   // Latch Register B
    output reg load_t,   // Latch Twiddle Register
    output reg ram_we,   // Write Enable for RAM
    output reg done      // Done Flag
);

    // ============================================================
    // 1. STATE MACHINE DEFINITIONS
    // ============================================================
    localparam S_IDLE   = 2'b00;
    localparam S_LOAD   = 2'b01; // Fetch A, B, W from RAM/ROM
    localparam S_WRITE  = 2'b10; // Compute & Write Result Back
    localparam S_UPDATE = 2'b11; // Increment Counters / Check Loops

    reg [1:0] state, next_state;

    // ============================================================
    // 2. INTERNAL COUNTERS (The "Registers" in your drawing)
    // ============================================================
    reg [3:0]   stage_cnt;  // Outer Loop (1 to 4)
    reg [M-1:0] group_cnt;  // Middle Loop (Group Index)
    reg [M-1:0] pair_cnt;   // Inner Loop (Pair Index)
    
    // The Shift Registers
    reg [M-1:0] span;       // Left Shift Register (<< 1)
    reg [M-1:0] num_groups; // Right Shift Register (>> 1)

    // ============================================================
    // 3. ADDRESS GENERATION LOGIC (The "Cloud")
    // ============================================================
    // Logic: AddrA = (Group * 2 * Span) + Pair
    // Logic: AddrB = AddrA + Span
    
    // Note: (Group * 2 * Span) is the same as (Group * (Span << 1))
    wire [M-1:0] group_offset = group_cnt * (span << 1);
    
    assign addr_a = group_offset + pair_cnt;
    assign addr_b = addr_a + span;

    // Twiddle Address Logic:
    // Matches the rotation speed needed for each stage.
    // Equivalent to: pair * (N / (2 * span))
    assign rom_addr = pair_cnt << (LOG2N - stage_cnt);

    // ============================================================
    // 4. SEQUENTIAL LOGIC (Counters & Shifts)
    // ============================================================
    always @(posedge clk or posedge rst) begin
        if (rst) begin
            state      <= S_IDLE;
            pair_cnt   <= 0;
            group_cnt  <= 0;
            stage_cnt  <= 1;
            
            // Initial Values
            span       <= 1;                    // Start Span = 1
            num_groups <= 1 << (LOG2N - 1);     // Start Groups = N/2 (e.g., 8)
            done       <= 0;
        end 
        else begin
            state <= next_state;

            // --- Counter Updates (Only in S_UPDATE state) ---
            if (state == S_UPDATE) begin
                
                // Priority 1: Inner Loop (Pairs)
                // "if pair_cnt < span - 1"
                if (pair_cnt < span - 1) begin
                    pair_cnt <= pair_cnt + 1;
                end 
                
                // Priority 2: Middle Loop (Groups)
                // "if group_cnt < num_groups - 1"
                else if (group_cnt < num_groups - 1) begin
                    pair_cnt  <= 0;              // Reset Pair
                    group_cnt <= group_cnt + 1;  // Next Group
                end 
                
                // Priority 3: Outer Loop (Stages)
                // "if stage_cnt < LOG2N"
                else if (stage_cnt < LOG2N) begin
                    pair_cnt   <= 0;
                    group_cnt  <= 0;
                    stage_cnt  <= stage_cnt + 1; // Next Stage
                    
                    // THE SHIFT REGISTERS UPDATE HERE
                    span       <= span << 1;     // Span Doubles (1->2->4)
                    num_groups <= num_groups >> 1; // Groups Halve (8->4->2)
                end 
                
                // Priority 4: Finish
                else begin
                    done <= 1;
                end
            end

            // Reset logic when starting a new run
            if (state == S_IDLE && start) begin
                done       <= 0;
                stage_cnt  <= 1;
                pair_cnt   <= 0;
                group_cnt  <= 0;
                span       <= 1;
                num_groups <= 1 << (LOG2N - 1);
            end
        end
    end

    // ============================================================
    // 5. NEXT STATE & OUTPUT LOGIC (The "Brain" Cloud)
    // ============================================================
    always @(*) begin
        // Default Assignments (Latch avoidance)
        next_state = state;
        load_a = 0; 
        load_b = 0; 
        load_t = 0; 
        ram_we = 0;

        case (state)
            // --- S_IDLE (MISSING IN YOUR CODE) ---
            S_IDLE: begin
                if (start) next_state = S_LOAD;
            end

            // --- S_LOAD ---
            S_LOAD: begin
                // Action: Fetch Data from RAM to Registers
                load_a = 1;
                load_b = 1;
                load_t = 1;
                
                // Unconditional Jump to Execute
                next_state = S_WRITE;
            end

            // --- S_WRITE ---
            S_WRITE: begin
                // Action: Write Math Result back to RAM
                ram_we = 1;
                
                // Unconditional Jump to Update Counters
                next_state = S_UPDATE;
            end

            // --- S_UPDATE (THE FIXED VERSION) ---
            S_UPDATE: begin
                // FIX: Check the actual counters directly.
                // If we are at the Last Stage + Last Group + Last Pair, we are finished.
                if (stage_cnt == LOG2N && group_cnt == num_groups - 1 && pair_cnt == span - 1) 
                    next_state = S_IDLE;
                else 
                    next_state = S_LOAD; // Not done, go fetch next pair
            end
        endcase
    end

endmodule

fft_top.v
module fft_top #(
    parameter N = 32, // Data Width
    parameter M = 4   // Address Width (Log2 N)
)(
    input wire clk,
    input wire rst,
    input wire start,
    output wire done,
    
    // Optional: Debug ports to see what's happening inside
    output wire [N-1:0] debug_data
);

    // ============================================================
    // 1. INTERNAL WIRES (The cables connecting the boxes)
    // ============================================================
    
    // Address Lines
    wire [M-1:0] addr_a_wire;
    wire [M-1:0] addr_b_wire;
    wire [M-1:0] rom_addr_wire;

    // Control Signals
    wire load_a_wire;
    wire load_b_wire;
    wire load_t_wire;
    wire ram_we_wire;

    // ============================================================
    // 2. INSTANTIATE THE BRAIN (Control Unit)
    // ============================================================
    control_unit #(
        .M(M), 
        .LOG2N(M) // If N=16, LOG2N is 4
    ) u_control (
        .clk(clk),
        .rst(rst),
        .start(start),
        
        // Outputs (The Commands)
        .addr_a(addr_a_wire),
        .addr_b(addr_b_wire),
        .rom_addr(rom_addr_wire),
        .load_a(load_a_wire),
        .load_b(load_b_wire),
        .load_t(load_t_wire),
        .ram_we(ram_we_wire),
        .done(done)
    );

    // ============================================================
    // 3. INSTANTIATE THE MUSCLES (Datapath)
    // ============================================================
    fft_datapath #(
        .N(N),
        .M(M)
    ) u_datapath (
        .clk(clk),
        
        // Inputs (Listening to the Brain)
        .addr_a(addr_a_wire),
        .addr_b(addr_b_wire),
        .rom_addr(rom_addr_wire),
        .load_a(load_a_wire),
        .load_b(load_b_wire),
        .load_t(load_t_wire),
        .ram_we(ram_we_wire),
        
        // Debug Output
        .debug_data_out(debug_data)
    );

endmodule

fft_tb.v
`timescale 1ns / 1ps

module fft_tb;

    // --- CONFIGURATION ---
    parameter N_WIDTH = 32;
    parameter M_ADDR  = 6;  // <--- CHANGED TO 6 (64 Points)
    
    reg clk, rst, start;
    wire done;
    wire [31:0] debug_data;

    fft_top #(.N(N_WIDTH), .M(M_ADDR)) uut (
        .clk(clk), .rst(rst), .start(start), .done(done), .debug_data(debug_data)
    );

    always #5 clk = ~clk;

    integer i;
    reg [M_ADDR-1:0] bit_rev;   // Variable to hold reversed address
    reg signed [15:0] wave_real; // Temp variable for math
    
    // Constants for Sine Generation
    real PI = 3.14159265;
    real freq = 4.0; // We want to see 4 cycles in the window

    initial begin
        // WAVEFORM DUMPING
        $dumpfile("fft.vcd");
        $dumpvars(0, fft_tb);

        clk = 0; rst = 1; start = 0;

        // --- BACKDOOR LOADING: 64-Point Sine Wave ---
        $display("Loading 64-Point Input Data...");
        
        for (i = 0; i < 64; i = i + 1) begin
            // 1. Generate High-Res Sine Wave using System Math
            // Amplitude 1000, Freq 4
            wave_real = $rtoi(1000.0 * $cos(2.0 * PI * freq * i / 64.0));
            
            // 2. Calculate Bit Reverse Address Automatically
            // For M=6: {0,1,2,3,4,5} -> {5,4,3,2,1,0}
            bit_rev[5] = i[0];
            bit_rev[4] = i[1];
            bit_rev[3] = i[2];
            bit_rev[2] = i[3];
            bit_rev[1] = i[4];
            bit_rev[0] = i[5];

            // 3. Load to RAM
            uut.u_datapath.data_mem.mem[bit_rev] = {wave_real, 16'd0};
        end

        // --- RUN FFT ---
        #100; rst = 0;
        #20;  start = 1;
        #10;  start = 0;

        wait(done);
        $display("FFT Done!");
        
        // --- PRINT RESULTS ---
        // Only print the first 10 and the spikes to keep terminal clean
        $display("Checking Index 4 and 60 (Mirrors)...");
        $display("Idx 4:  %d", $signed(uut.u_datapath.data_mem.mem[4][31:16]));
        $display("Idx 60: %d", $signed(uut.u_datapath.data_mem.mem[60][31:16]));

        #100;
        $stop;
    end
endmodule

fft.vcd
$date
	Thu Jan  1 18:28:31 2026
$end
$version
	Icarus Verilog
$end
$timescale
	1ps
$end
$scope module fft_tb $end
$var wire 1 ! done $end
$var wire 32 " debug_data [31:0] $end
$var parameter 32 # M_ADDR $end
$var parameter 32 $ N_WIDTH $end
$var reg 6 % bit_rev [5:0] $end
$var reg 1 & clk $end
$var reg 1 ' rst $end
$var reg 1 ( start $end
$var reg 16 ) wave_real [15:0] $end
$var real 1 * PI $end
$var real 1 + freq $end
$var integer 32 , i [31:0] $end
$scope module uut $end
$var wire 1 & clk $end
$var wire 1 ' rst $end
$var wire 1 ( start $end
$var wire 6 - rom_addr_wire [5:0] $end
$var wire 1 . ram_we_wire $end
$var wire 1 / load_t_wire $end
$var wire 1 0 load_b_wire $end
$var wire 1 1 load_a_wire $end
$var wire 1 ! done $end
$var wire 32 2 debug_data [31:0] $end
$var wire 6 3 addr_b_wire [5:0] $end
$var wire 6 4 addr_a_wire [5:0] $end
$var parameter 32 5 M $end
$var parameter 32 6 N $end
$scope module u_control $end
$var wire 1 & clk $end
$var wire 1 ' rst $end
$var wire 1 ( start $end
$var wire 6 7 rom_addr [5:0] $end
$var wire 6 8 group_offset [5:0] $end
$var wire 6 9 addr_b [5:0] $end
$var wire 6 : addr_a [5:0] $end
$var parameter 32 ; LOG2N $end
$var parameter 32 < M $end
$var parameter 2 = S_IDLE $end
$var parameter 2 > S_LOAD $end
$var parameter 2 ? S_UPDATE $end
$var parameter 2 @ S_WRITE $end
$var reg 1 ! done $end
$var reg 6 A group_cnt [5:0] $end
$var reg 1 1 load_a $end
$var reg 1 0 load_b $end
$var reg 1 / load_t $end
$var reg 2 B next_state [1:0] $end
$var reg 6 C num_groups [5:0] $end
$var reg 6 D pair_cnt [5:0] $end
$var reg 1 . ram_we $end
$var reg 6 E span [5:0] $end
$var reg 4 F stage_cnt [3:0] $end
$var reg 2 G state [1:0] $end
$upscope $end
$scope module u_datapath $end
$var wire 6 H addr_a [5:0] $end
$var wire 6 I addr_b [5:0] $end
$var wire 1 & clk $end
$var wire 32 J debug_data_out [31:0] $end
$var wire 1 1 load_a $end
$var wire 1 0 load_b $end
$var wire 1 / load_t $end
$var wire 1 . ram_we $end
$var wire 6 K rom_addr [5:0] $end
$var wire 32 L write_data_b [31:0] $end
$var wire 32 M write_data_a [31:0] $end
$var wire 16 N tr [15:0] $end
$var wire 16 O ti [15:0] $end
$var wire 32 P rom_out_t [31:0] $end
$var wire 32 Q ram_out_b [31:0] $end
$var wire 32 R ram_out_a [31:0] $end
$var wire 16 S new_br [15:0] $end
$var wire 16 T new_bi [15:0] $end
$var wire 16 U new_ar [15:0] $end
$var wire 16 V new_ai [15:0] $end
$var parameter 32 W M $end
$var parameter 32 X N $end
$var reg 16 Y reg_ai [15:0] $end
$var reg 16 Z reg_ar [15:0] $end
$var reg 16 [ reg_bi [15:0] $end
$var reg 16 \ reg_br [15:0] $end
$var reg 16 ] reg_wi [15:0] $end
$var reg 16 ^ reg_wr [15:0] $end
$scope module data_mem $end
$var wire 6 _ addr_a [5:0] $end
$var wire 6 ` addr_b [5:0] $end
$var wire 1 & clk $end
$var wire 32 a din_a [31:0] $end
$var wire 32 b din_b [31:0] $end
$var wire 32 c dout_a [31:0] $end
$var wire 32 d dout_b [31:0] $end
$var wire 1 . we_a $end
$var wire 1 . we_b $end
$var parameter 32 e ADDR_WIDTH $end
$var parameter 32 f DATA_WIDTH $end
$upscope $end
$scope module twiddle_mem $end
$var wire 6 g addr [5:0] $end
$var parameter 32 h ADDR_WIDTH $end
$var parameter 32 i DATA_WIDTH $end
$var reg 32 j dout [31:0] $end
$upscope $end
$scope module u_add $end
$var wire 16 k ai [15:0] $end
$var wire 16 l ar [15:0] $end
$var wire 16 m tr [15:0] $end
$var wire 16 n top_r [15:0] $end
$var wire 16 o top_i [15:0] $end
$var wire 16 p ti [15:0] $end
$var wire 16 q bot_r [15:0] $end
$var wire 16 r bot_i [15:0] $end
$upscope $end
$scope module u_mult $end
$var wire 16 s bi [15:0] $end
$var wire 16 t br [15:0] $end
$var wire 16 u wi [15:0] $end
$var wire 16 v wr [15:0] $end
$var wire 32 w tr_full [31:0] $end
$var wire 16 x tr [15:0] $end
$var wire 32 y ti_full [31:0] $end
$var wire 16 z ti [15:0] $end
$var wire 32 { k4 [31:0] $end
$var wire 32 | k3 [31:0] $end
$var wire 32 } k2 [31:0] $end
$var wire 32 ~ k1 [31:0] $end
$upscope $end
$upscope $end
$upscope $end
$upscope $end
$enddefinitions $end
$comment Show the parameter values. $end
$dumpall
b100000 i
b110 h
b100000 f
b110 e
b100000 X
b110 W
b10 @
b11 ?
b1 >
b0 =
b110 <
b110 ;
b100000 6
b110 5
b100000 $
b110 #
$end
#0
$dumpvars
bx ~
bx }
bx |
bx {
bx z
bx y
bx x
bx w
bx v
bx u
bx t
bx s
bx r
bx q
bx p
bx o
bx n
bx m
bx l
bx k
b1000000000000000000000000000000 j
b0 g
b11111001110000000000000000 d
b11111010000000000000000000 c
bx b
bx a
b1 `
b0 _
bx ^
bx ]
bx \
bx [
bx Z
bx Y
bx V
bx U
bx T
bx S
b11111010000000000000000000 R
b11111001110000000000000000 Q
b1000000000000000000000000000000 P
bx O
bx N
bx M
bx L
b0 K
bx J
b1 I
b0 H
b0 G
b1 F
b1 E
b0 D
b100000 C
b0 B
b0 A
b0 :
b1 9
b0 8
b0 7
b0 4
b1 3
bx 2
01
00
0/
0.
b0 -
b1000000 ,
r4 +
r3.14159265 *
b1110011011 )
0(
1'
0&
b111111 %
bx "
0!
$end
#5000
1&
#10000
0&
#15000
1&
#20000
0&
#25000
1&
#30000
0&
#35000
1&
#40000
0&
#45000
1&
#50000
0&
#55000
1&
#60000
0&
#65000
1&
#70000
0&
#75000
1&
#80000
0&
#85000
1&
#90000
0&
#95000
1&
#100000
0&
0'
#105000
1&
#110000
0&
#115000
1&
#120000
b1 B
0&
1(
#125000
b10 B
1/
10
11
b1 G
1&
#130000
1/
10
11
b10 B
0&
0(
#135000
b11 B
1.
0/
00
01
b1 S
b1 q
b11111001111 U
b11111001111 n
b1111100111 N
b1111100111 m
b1111100111 x
b10000000000000000 L
b10000000000000000 b
b0 T
b0 r
b111110011110000000000000000 "
b111110011110000000000000000 2
b111110011110000000000000000 J
b111110011110000000000000000 M
b111110011110000000000000000 a
b0 V
b0 o
b0 O
b0 p
b0 z
b10 G
b111110011100000000000000 w
b0 }
b0 y
b0 |
b0 ]
b0 u
b111110011100000000000000 ~
b0 {
b100000000000000 ^
b100000000000000 v
b0 [
b0 s
b1111100111 \
b1111100111 t
b0 Y
b0 k
b1111101000 Z
b1111101000 l
1&
#140000
0&
#145000
b1 B
0.
b11 G
b10000000000000000 Q
b10000000000000000 d
b111110011110000000000000000 R
b111110011110000000000000000 c
1&
#150000
0&
#155000
b10 B
1/
10
11
b11111001110000000000000000 Q
b11111001110000000000000000 d
b11 3
b11 9
b11 I
b11 `
b11111010000000000000000000 R
b11111010000000000000000000 c
b10 4
b10 :
b10 H
b10 _
b10 8
b1 A
b1 G
1&
#160000
0&
#165000
b11 B
1.
0/
00
01
b10 G
1&
#170000
0&
#175000
b1 B
0.
b11 G
b10000000000000000 Q
b10000000000000000 d
b111110011110000000000000000 R
b111110011110000000000000000 c
1&
#180000
0&
#185000
b10 B
1/
10
11
b11111100000110010000000000000000 Q
b11111100000110010000000000000000 d
b101 3
b101 9
b101 I
b101 `
b11111100000110000000000000000000 R
b11111100000110000000000000000000 c
b100 4
b100 :
b100 H
b100 _
b100 8
b10 A
b1 G
1&
#190000
0&
#195000
b11 B
1.
0/
00
01
b1111110000011001 N
b1111110000011001 m
b1111110000011001 x
b10 G
b11111111000001100100000000000000 w
b11111111000001100100000000000000 ~
b1111110000011001 \
b1111110000011001 t
b11111000001100010000000000000000 "
b11111000001100010000000000000000 2
b11111000001100010000000000000000 J
b11111000001100010000000000000000 M
b11111000001100010000000000000000 a
b1111100000110001 U
b1111100000110001 n
b11111111111111110000000000000000 L
b11111111111111110000000000000000 b
b1111111111111111 S
b1111111111111111 q
b1111110000011000 Z
b1111110000011000 l
1&
#200000
0&
#205000
b1 B
0.
b11 G
b11111111111111110000000000000000 Q
b11111111111111110000000000000000 d
b11111000001100010000000000000000 R
b11111000001100010000000000000000 c
1&
#210000
0&
#215000
b10 B
1/
10
11
b11111100000110010000000000000000 Q
b11111100000110010000000000000000 d
b111 3
b111 9
b111 I
b111 `
b11111100000110010000000000000000 R
b11111100000110010000000000000000 c
b110 4
b110 :
b110 H
b110 _
b110 8
b11 A
b1 G
1&
#220000
0&
#225000
b11 B
1.
0/
00
01
b10 G
b11111000001100100000000000000000 "
b11111000001100100000000000000000 2
b11111000001100100000000000000000 J
b11111000001100100000000000000000 M
b11111000001100100000000000000000 a
b1111100000110010 U
b1111100000110010 n
b0 L
b0 b
b0 S
b0 q
b1111110000011001 Z
b1111110000011001 l
1&
#230000
0&
#235000
b1 B
0.
b11 G
b0 Q
b0 d
b11111000001100100000000000000000 R
b11111000001100100000000000000000 c
1&
#240000
0&
#245000
b10 B
1/
10
11
b1001 3
b1001 9
b1001 I
b1001 `
b0 R
b0 c
b1000 4
b1000 :
b1000 H
b1000 _
b1000 8
b100 A
b1 G
1&
#250000
0&
#255000
b11 B
1.
0/
00
01
b0 N
b0 m
b0 x
b10 G
b0 w
b0 ~
b0 \
b0 t
b0 "
b0 2
b0 J
b0 M
b0 a
b0 U
b0 n
b0 L
b0 b
b0 S
b0 q
b0 Z
b0 l
1&
#260000
0&
#265000
b1 B
0.
b11 G
1&
#270000
0&
#275000
b10 B
1/
10
11
b1011 3
b1011 9
b1011 I
b1011 `
b1010 4
b1010 :
b1010 H
b1010 _
b1010 8
b101 A
b1 G
1&
#280000
0&
#285000
b11 B
1.
0/
00
01
b10 G
1&
#290000
0&
#295000
b1 B
0.
b11 G
1&
#300000
0&
#305000
b10 B
1/
10
11
b1101 3
b1101 9
b1101 I
b1101 `
b1100 4
b1100 :
b1100 H
b1100 _
b1100 8
b110 A
b1 G
1&
#310000
0&
#315000
b11 B
1.
0/
00
01
b10 G
1&
#320000
0&
#325000
b1 B
0.
b11 G
1&
#330000
0&
#335000
b10 B
1/
10
11
b1111 3
b1111 9
b1111 I
b1111 `
b1110 4
b1110 :
b1110 H
b1110 _
b1110 8
b111 A
b1 G
1&
#340000
0&
#345000
b11 B
1.
0/
00
01
b10 G
1&
#350000
0&
#355000
b1 B
0.
b11 G
1&
#360000
0&
#365000
b10 B
1/
10
11
b10110000110000000000000000 Q
b10110000110000000000000000 d
b10001 3
b10001 9
b10001 I
b10001 `
b10110000110000000000000000 R
b10110000110000000000000000 c
b10000 4
b10000 :
b10000 H
b10000 _
b10000 8
b1000 A
b1 G
1&
#370000
0&
#375000
b11 B
1.
0/
00
01
b1011000011 N
b1011000011 m
b1011000011 x
b10 G
b101100001100000000000000 w
b101100001100000000000000 ~
b1011000011 \
b1011000011 t
b101100001100000000000000000 "
b101100001100000000000000000 2
b101100001100000000000000000 J
b101100001100000000000000000 M
b101100001100000000000000000 a
b10110000110 U
b10110000110 n
b0 L
b0 b
b0 S
b0 q
b1011000011 Z
b1011000011 l
1&
#380000
0&
#385000
b1 B
0.
b11 G
b0 Q
b0 d
b101100001100000000000000000 R
b101100001100000000000000000 c
1&
#390000
0&
#395000
b10 B
1/
10
11
b10110000110000000000000000 Q
b10110000110000000000000000 d
b10011 3
b10011 9
b10011 I
b10011 `
b10110000110000000000000000 R
b10110000110000000000000000 c
b10010 4
b10010 :
b10010 H
b10010 _
b10010 8
b1001 A
b1 G
1&
#400000
0&
#405000
b11 B
1.
0/
00
01
b10 G
1&
#410000
0&
#415000
b1 B
0.
b11 G
b0 Q
b0 d
b101100001100000000000000000 R
b101100001100000000000000000 c
1&
#420000
0&
#425000
b10 B
1/
10
11
b11111101001111010000000000000000 Q
b11111101001111010000000000000000 d
b10101 3
b10101 9
b10101 I
b10101 `
b11111101001111010000000000000000 R
b11111101001111010000000000000000 c
b10100 4
b10100 :
b10100 H
b10100 _
b10100 8
b1010 A
b1 G
1&
#430000
0&
#435000
b11 B
1.
0/
00
01
b1111110100111101 N
b1111110100111101 m
b1111110100111101 x
b10 G
b11111111010011110100000000000000 w
b11111111010011110100000000000000 ~
b1111110100111101 \
b1111110100111101 t
b11111010011110100000000000000000 "
b11111010011110100000000000000000 2
b11111010011110100000000000000000 J
b11111010011110100000000000000000 M
b11111010011110100000000000000000 a
b1111101001111010 U
b1111101001111010 n
b0 L
b0 b
b0 S
b0 q
b1111110100111101 Z
b1111110100111101 l
1&
#440000
0&
#445000
b1 B
0.
b11 G
b0 Q
b0 d
b11111010011110100000000000000000 R
b11111010011110100000000000000000 c
1&
#450000
0&
#455000
b10 B
1/
10
11
b11111101001111010000000000000000 Q
b11111101001111010000000000000000 d
b10111 3
b10111 9
b10111 I
b10111 `
b11111101001111010000000000000000 R
b11111101001111010000000000000000 c
b10110 4
b10110 :
b10110 H
b10110 _
b10110 8
b1011 A
b1 G
1&
#460000
0&
#465000
b11 B
1.
0/
00
01
b10 G
1&
#470000
0&
#475000
b1 B
0.
b11 G
b0 Q
b0 d
b11111010011110100000000000000000 R
b11111010011110100000000000000000 c
1&
#480000
0&
